camgeos/__init__.py
camgeos/camgeos.py
camgeos-0.0.4.dist-info/LICENSE
camgeos-0.0.4.dist-info/METADATA
camgeos-0.0.4.dist-info/WHEEL
camgeos-0.0.4.dist-info/top_level.txt
camgeos-0.0.4.dist-info/RECORD
