Metadata-Version: 2.1
Name: camgeos
Version: 0.0.4
Summary: This is my demo python package.
Home-page: https://github.com/chungsarit/camgeos
Author: Chung Sarit
Author-email: sarithchung168@gmail.com
License: MIT license
Keywords: camgeos
Classifier: Development Status :: 2 - Pre-Alpha
Classifier: Intended Audience :: Developers
Classifier: License :: OSI Approved :: MIT License
Classifier: Natural Language :: English
Classifier: Programming Language :: Python :: 3
Classifier: Programming Language :: Python :: 3.7
Classifier: Programming Language :: Python :: 3.8
Classifier: Programming Language :: Python :: 3.9
Classifier: Programming Language :: Python :: 3.10
Requires-Python: >=3.7
License-File: LICENSE
